{
  "parent": "minecraft:recipes/root",
  "rewards": {
    "recipes": [
      "structurize:green_clay_jungle_shingle"
    ]
  },
  "criteria": {
    "has_green_clay_jungle_shingle": {
      "trigger": "minecraft:inventory_changed",
      "conditions": {
        "items": [
          {
            "item": "structurize:green_clay_jungle_shingle"
          }
        ]
      }
    },
    "has_the_recipe": {
      "trigger": "minecraft:recipe_unlocked",
      "conditions": {
        "recipe": "structurize:green_clay_jungle_shingle"
      }
    }
  },
  "requirements": [
    [
      "has_green_clay_jungle_shingle",
      "has_the_recipe"
    ]
  ]
}